{
  "collapse-filter": true,
  "search": "",
  "showTags": false,
  "showAttachments": false,
  "hideUnresolved": false,
  "showOrphans": true,
  "collapse-color-groups": true,
  "colorGroups": [
    {
      "query": "file:README",
      "color": {
        "a": 1,
        "rgb": 14048348
      }
    },
    {
      "query": "file:index",
      "color": {
        "a": 1,
        "rgb": 7719299
      }
    }
  ],
  "collapse-display": false,
  "showArrow": false,
  "textFadeMultiplier": -0.9,
  "nodeSizeMultiplier": 1.41614695893794,
  "lineSizeMultiplier": 4.72739117011423,
  "collapse-forces": false,
  "centerStrength": 0,
  "repelStrength": 6.55757949984563,
  "linkStrength": 1,
  "linkDistance": 310,
  "scale": 0.45191403788562734,
  "close": false
}